mwsdk/__init__.py
mwsdk/auth.py
mwsdk/kong.py
mwsdk/rightmanage.py
mwsdk-0.3.3.dist-info/licenses/LICENSE.txt
mwsdk-0.3.3.dist-info/METADATA
mwsdk-0.3.3.dist-info/WHEEL
mwsdk-0.3.3.dist-info/top_level.txt
mwsdk-0.3.3.dist-info/RECORD
