Metadata-Version: 2.4
Name: mwsdk
Version: 0.3.3
Summary: maxwin 框架的sdk
Home-page: https://bitbucket.org/maxwin-inc/mwsdk/src
Author: cxhjet
Author-email: 13064576@qq.com
Classifier: Intended Audience :: Developers
Classifier: License :: OSI Approved :: BSD License
Classifier: Operating System :: OS Independent
Classifier: Programming Language :: Python :: 3.5
Classifier: Programming Language :: Python :: 3.6
License-File: LICENSE.txt
Requires-Dist: aiohttp>=3.2.0
Requires-Dist: mwutils>=0.1.41
Dynamic: author
Dynamic: author-email
Dynamic: classifier
Dynamic: description
Dynamic: description-content-type
Dynamic: home-page
Dynamic: license-file
Dynamic: requires-dist
Dynamic: summary
